{"name":null,"assets":"aoy4:pathy55:assets%2Fweek6%2Fimages%2Fweeb%2FanimatedEvilSchool.pngy4:sizei86440y4:typey5:IMAGEy2:idR1goR0y55:assets%2Fweek6%2Fimages%2Fweeb%2FanimatedEvilSchool.xmlR2i3887R3y4:TEXTR5R6goR0y59:assets%2Fweek6%2Fimages%2Fweeb%2FanimatedEvilSchool_low.pngR2i6780R3R4R5R8goR0y47:assets%2Fweek6%2Fimages%2Fweeb%2FbfPortrait.pngR2i3156R3R4R5R9goR0y47:assets%2Fweek6%2Fimages%2Fweeb%2FbfPortrait.xmlR2i1126R3R7R5R10goR0y45:assets%2Fweek6%2Fimages%2Fweeb%2FbgFreaks.pngR2i30914R3R4R5R11goR0y45:assets%2Fweek6%2Fimages%2Fweeb%2FbgFreaks.xmlR2i5211R3R7R5R12goR0y45:assets%2Fweek6%2Fimages%2Fweeb%2FbgGhouls.pngR2i19521R3R4R5R13goR0y45:assets%2Fweek6%2Fimages%2Fweeb%2FbgGhouls.xmlR2i1985R3R7R5R14goR0y49:assets%2Fweek6%2Fimages%2Fweeb%2FevilSchoolBG.pngR2i4774R3R4R5R15goR0y49:assets%2Fweek6%2Fimages%2Fweeb%2FevilSchoolFG.pngR2i1774R3R4R5R16goR0y43:assets%2Fweek6%2Fimages%2Fweeb%2Fpetals.pngR2i1617R3R4R5R17goR0y43:assets%2Fweek6%2Fimages%2Fweeb%2Fpetals.xmlR2i4557R3R7R5R18goR0y63:assets%2Fweek6%2Fimages%2Fweeb%2FpixelUI%2FdialogueBox-evil.pngR2i209R3R4R5R19goR0y63:assets%2Fweek6%2Fimages%2Fweeb%2FpixelUI%2FdialogueBox-evil.xmlR2i1385R3R7R5R20goR0y64:assets%2Fweek6%2Fimages%2Fweeb%2FpixelUI%2FdialogueBox-pixel.pngR2i2618R3R4R5R21goR0y64:assets%2Fweek6%2Fimages%2Fweeb%2FpixelUI%2FdialogueBox-pixel.xmlR2i680R3R7R5R22goR0y68:assets%2Fweek6%2Fimages%2Fweeb%2FpixelUI%2FdialogueBox-senpaiMad.pngR2i8391R3R4R5R23goR0y68:assets%2Fweek6%2Fimages%2Fweeb%2FpixelUI%2FdialogueBox-senpaiMad.xmlR2i1050R3R7R5R24goR0y59:assets%2Fweek6%2Fimages%2Fweeb%2FpixelUI%2Fhand_textbox.pngR2i171R3R4R5R25goR0y48:assets%2Fweek6%2Fimages%2Fweeb%2FsenpaiCrazy.pngR2i5503R3R4R5R26goR0y48:assets%2Fweek6%2Fimages%2Fweeb%2FsenpaiCrazy.xmlR2i19805R3R7R5R27goR0y51:assets%2Fweek6%2Fimages%2Fweeb%2FsenpaiPortrait.pngR2i4656R3R4R5R28goR0y51:assets%2Fweek6%2Fimages%2Fweeb%2FsenpaiPortrait.xmlR2i1103R3R7R5R29goR0y54:assets%2Fweek6%2Fimages%2Fweeb%2FspiritFaceForward.pngR2i787R3R4R5R30goR0y50:assets%2Fweek6%2Fimages%2Fweeb%2FweebTreesBack.pngR2i663R3R4R5R31goR0y43:assets%2Fweek6%2Fmusic%2FgameOver-pixel.oggR2i1625233R3y5:MUSICR5R32goR0y46:assets%2Fweek6%2Fmusic%2FgameOverEnd-pixel.oggR2i94419R3y5:SOUNDR5R34goR0y37:assets%2Fweek6%2Fmusic%2FLunchbox.oggR2i491250R3R35R5R36goR0y42:assets%2Fweek6%2Fmusic%2FLunchboxScary.oggR2i253221R3R35R5R37goR0y48:assets%2Fweek6%2Fsounds%2Ffnf_loss_sfx-pixel.oggR2i64518R3R35R5R38goR0y39:assets%2Fweek6%2Fsounds%2FpixelText.oggR2i4567R3R35R5R39goR0y41:assets%2Fweek6%2Fsounds%2FSenpai_Dies.oggR2i136579R3R35R5R40goR0y37:assets%2Fweek6%2Fweek6_stuff_here.txtR2zR3R7R5R41gh","rootPath":"../","version":2,"libraryArgs":[],"libraryType":null}